battleshippygame/__init__.py
battleshippygame/battleshippygame.py
battleshippygame-1.0.0.dist-info/LICENSE.txt
battleshippygame-1.0.0.dist-info/METADATA
battleshippygame-1.0.0.dist-info/WHEEL
battleshippygame-1.0.0.dist-info/top_level.txt
battleshippygame-1.0.0.dist-info/RECORD
